{
    "identifier": "NESCIO",
    "conuigazione": "4",
    "translation": [
        "(assoluto o + accusativo) ignorare",
        "non sapere",
        "non conoscere",
        "(+ infinito o + accusativo e infinito) non riuscire",
        "non potere"
    ],
    "valid_translations": [],
    "INDICATIVO": {
        "PRESENTE": [
            {
                "persona": "I sing.",
                "verbo": "nescĭo",
                "traduzioni": []
            },
            {
                "persona": "II sing.",
                "verbo": "nescis",
                "traduzioni": []
            },
            {
                "persona": "III sing.",
                "verbo": "nescit",
                "traduzioni": []
            },
            {
                "persona": "I plur.",
                "verbo": "nescīmus",
                "traduzioni": []
            },
            {
                "persona": "II plur.",
                "verbo": "nescītis",
                "traduzioni": []
            },
            {
                "persona": "III plur.",
                "verbo": "nescĭunt",
                "traduzioni": []
            }
        ],
        "IMPERFETTO": [
            {
                "persona": "I sing.",
                "verbo": "nesciēbam",
                "traduzioni": []
            },
            {
                "persona": "II sing.",
                "verbo": "nesciēbas",
                "traduzioni": []
            },
            {
                "persona": "III sing.",
                "verbo": "nesciēbat",
                "traduzioni": []
            },
            {
                "persona": "I plur.",
                "verbo": "nesciebāmus",
                "traduzioni": []
            },
            {
                "persona": "II plur.",
                "verbo": "nesciebātis",
                "traduzioni": []
            },
            {
                "persona": "III plur.",
                "verbo": "nesciēbant",
                "traduzioni": []
            }
        ],
        "FUTURO SEMPLICE": [
            {
                "persona": "I sing.",
                "verbo": "nescĭam",
                "traduzioni": []
            },
            {
                "persona": "II sing.",
                "verbo": "nescĭes",
                "traduzioni": []
            },
            {
                "persona": "III sing.",
                "verbo": "nescĭet",
                "traduzioni": []
            },
            {
                "persona": "I plur.",
                "verbo": "nesciēmus",
                "traduzioni": []
            },
            {
                "persona": "II plur.",
                "verbo": "nesciētis",
                "traduzioni": []
            },
            {
                "persona": "III plur.",
                "verbo": "nescĭent",
                "traduzioni": []
            }
        ],
        "PERFETTO": [
            {
                "persona": "I sing.",
                "verbo": "nescii o nescivi",
                "traduzioni": []
            },
            {
                "persona": "II sing.",
                "verbo": "nesciisti o nescivisti",
                "traduzioni": []
            },
            {
                "persona": "III sing.",
                "verbo": "nesciit o nescivit",
                "traduzioni": []
            },
            {
                "persona": "I plur.",
                "verbo": "nesciĭmus o nescivĭmus",
                "traduzioni": []
            },
            {
                "persona": "II plur.",
                "verbo": "nesciistis o nescivistis",
                "traduzioni": []
            },
            {
                "persona": "III plur.",
                "verbo": "nesciērunt o nescivērunt, ēre",
                "traduzioni": []
            }
        ],
        "PIUCHEPERFETTO": [
            {
                "persona": "I sing.",
                "verbo": "nesciĕram o nescivĕram",
                "traduzioni": []
            },
            {
                "persona": "II sing.",
                "verbo": "nesciĕras o nescivĕras",
                "traduzioni": []
            },
            {
                "persona": "III sing.",
                "verbo": "nesciĕrat o nescivĕrat",
                "traduzioni": []
            },
            {
                "persona": "I plur.",
                "verbo": "nescierāmus o nesciverāmus",
                "traduzioni": []
            },
            {
                "persona": "II plur.",
                "verbo": "nescierātis o nesciverātis",
                "traduzioni": []
            },
            {
                "persona": "III plur.",
                "verbo": "nesciĕrant o nescivĕrant",
                "traduzioni": []
            }
        ],
        "FUTURO ANTERIORE": [
            {
                "persona": "I sing.",
                "verbo": "nesciĕro o nescivĕro",
                "traduzioni": []
            },
            {
                "persona": "II sing.",
                "verbo": "nesciĕris o nescivĕris",
                "traduzioni": []
            },
            {
                "persona": "III sing.",
                "verbo": "nesciĕrit o nescivĕrit",
                "traduzioni": []
            },
            {
                "persona": "I plur.",
                "verbo": "nescierĭmus o nesciverĭmus",
                "traduzioni": []
            },
            {
                "persona": "II plur.",
                "verbo": "nescierĭtis o nesciverĭtis",
                "traduzioni": []
            },
            {
                "persona": "III plur.",
                "verbo": "nesciĕrint o nescivĕrint",
                "traduzioni": []
            }
        ]
    },
    "CONGIUNTIVO": {
        "PRESENTE": [
            {
                "persona": "I sing.",
                "verbo": "nescĭam",
                "traduzioni": []
            },
            {
                "persona": "II sing.",
                "verbo": "nescĭas",
                "traduzioni": []
            },
            {
                "persona": "III sing.",
                "verbo": "nescĭat",
                "traduzioni": []
            },
            {
                "persona": "I plur.",
                "verbo": "nesciāmus",
                "traduzioni": []
            },
            {
                "persona": "II plur.",
                "verbo": "nesciātis",
                "traduzioni": []
            },
            {
                "persona": "III plur.",
                "verbo": "nescĭant",
                "traduzioni": []
            }
        ],
        "IMPERFETTO": [
            {
                "persona": "I sing.",
                "verbo": "nescīrem",
                "traduzioni": []
            },
            {
                "persona": "II sing.",
                "verbo": "nescīres",
                "traduzioni": []
            },
            {
                "persona": "III sing.",
                "verbo": "nescīret",
                "traduzioni": []
            },
            {
                "persona": "I plur.",
                "verbo": "nescirēmus",
                "traduzioni": []
            },
            {
                "persona": "II plur.",
                "verbo": "nescirētis",
                "traduzioni": []
            },
            {
                "persona": "III plur.",
                "verbo": "nescīrent",
                "traduzioni": []
            }
        ],
        "PERFETTO": [
            {
                "persona": "I sing.",
                "verbo": "nesciĕrim o nescivĕrim",
                "traduzioni": []
            },
            {
                "persona": "II sing.",
                "verbo": "nesciĕris o nescivĕris",
                "traduzioni": []
            },
            {
                "persona": "III sing.",
                "verbo": "nesciĕrit o nescivĕrit",
                "traduzioni": []
            },
            {
                "persona": "I plur.",
                "verbo": "nescierĭmus o nesciverĭmus",
                "traduzioni": []
            },
            {
                "persona": "II plur.",
                "verbo": "nescierĭtis o nesciverĭtis",
                "traduzioni": []
            },
            {
                "persona": "III plur.",
                "verbo": "nesciĕrint o nescivĕrint",
                "traduzioni": []
            }
        ],
        "PIUCHEPERFETTO": [
            {
                "persona": "I sing.",
                "verbo": "nesciissem o nescivissem",
                "traduzioni": []
            },
            {
                "persona": "II sing.",
                "verbo": "nesciisses o nescivisses",
                "traduzioni": []
            },
            {
                "persona": "III sing.",
                "verbo": "nesciisset o nescivisset",
                "traduzioni": []
            },
            {
                "persona": "I plur.",
                "verbo": "nesciissēmus o nescivissēmus",
                "traduzioni": []
            },
            {
                "persona": "II plur.",
                "verbo": "nesciissētis o nescivissētis",
                "traduzioni": []
            },
            {
                "persona": "III plur.",
                "verbo": "nesciissent o nescivissent",
                "traduzioni": []
            }
        ]
    }
}