{
    "identifier": "OBTEGO",
    "conuigazione": "3",
    "translation": [
        "nascondere",
        "celare",
        "coprire",
        "coprire",
        "proteggere",
        "riparare",
        "nascondere",
        "dissimulare"
    ],
    "valid_translations": [
        "nascondere",
        "celare",
        "coprire",
        "coprire",
        "proteggere",
        "riparare",
        "nascondere",
        "dissimulare"
    ],
    "INDICATIVO": {
        "PRESENTE": [
            {
                "persona": "I sing.",
                "verbo": "obtĕgo",
                "traduzioni": [
                    "io nascondo",
                    "io celo",
                    "io copro",
                    "io copro",
                    "io proteggo",
                    "io riparo",
                    "io nascondo",
                    "io dissimulo"
                ]
            },
            {
                "persona": "II sing.",
                "verbo": "obtĕgis",
                "traduzioni": [
                    "tu nascondi",
                    "tu celi",
                    "tu copri",
                    "tu copri",
                    "tu proteggi",
                    "tu ripari",
                    "tu nascondi",
                    "tu dissimuli"
                ]
            },
            {
                "persona": "III sing.",
                "verbo": "obtĕgit",
                "traduzioni": [
                    "lui nasconde",
                    "lei nasconde",
                    "egli nasconde",
                    "lui cela",
                    "lei cela",
                    "egli cela",
                    "lui copre",
                    "lei copre",
                    "egli copre",
                    "lui copre",
                    "lei copre",
                    "egli copre",
                    "lui protegge",
                    "lei protegge",
                    "egli protegge",
                    "lui ripara",
                    "lei ripara",
                    "egli ripara",
                    "lui nasconde",
                    "lei nasconde",
                    "egli nasconde",
                    "lui dissimula",
                    "lei dissimula",
                    "egli dissimula"
                ]
            },
            {
                "persona": "I plur.",
                "verbo": "obtĕgĭmus",
                "traduzioni": [
                    "noi nascondiamo",
                    "noi celiamo",
                    "noi copriamo",
                    "noi copriamo",
                    "noi proteggiamo",
                    "noi ripariamo",
                    "noi nascondiamo",
                    "noi dissimuliamo"
                ]
            },
            {
                "persona": "II plur.",
                "verbo": "obtĕgĭtis",
                "traduzioni": [
                    "voi nascondete",
                    "voi celate",
                    "voi coprite",
                    "voi coprite",
                    "voi proteggete",
                    "voi riparate",
                    "voi nascondete",
                    "voi dissimulate"
                ]
            },
            {
                "persona": "III plur.",
                "verbo": "obtĕgunt",
                "traduzioni": [
                    "loro nascondono",
                    "essi nascondono",
                    "loro celano",
                    "essi celano",
                    "loro coprono",
                    "essi coprono",
                    "loro coprono",
                    "essi coprono",
                    "loro proteggono",
                    "essi proteggono",
                    "loro riparano",
                    "essi riparano",
                    "loro nascondono",
                    "essi nascondono",
                    "loro dissimulano",
                    "essi dissimulano"
                ]
            }
        ],
        "IMPERFETTO": [
            {
                "persona": "I sing.",
                "verbo": "obtĕgēbam",
                "traduzioni": [
                    "io nascondevo",
                    "io celavo",
                    "io coprivo",
                    "io coprivo",
                    "io proteggevo",
                    "io riparavo",
                    "io nascondevo",
                    "io dissimulavo"
                ]
            },
            {
                "persona": "II sing.",
                "verbo": "obtĕgēbas",
                "traduzioni": [
                    "tu nascondevi",
                    "tu celavi",
                    "tu coprivi",
                    "tu coprivi",
                    "tu proteggevi",
                    "tu riparavi",
                    "tu nascondevi",
                    "tu dissimulavi"
                ]
            },
            {
                "persona": "III sing.",
                "verbo": "obtĕgēbat",
                "traduzioni": [
                    "lui nascondeva",
                    "lei nascondeva",
                    "egli nascondeva",
                    "lui celava",
                    "lei celava",
                    "egli celava",
                    "lui copriva",
                    "lei copriva",
                    "egli copriva",
                    "lui copriva",
                    "lei copriva",
                    "egli copriva",
                    "lui proteggeva",
                    "lei proteggeva",
                    "egli proteggeva",
                    "lui riparava",
                    "lei riparava",
                    "egli riparava",
                    "lui nascondeva",
                    "lei nascondeva",
                    "egli nascondeva",
                    "lui dissimulava",
                    "lei dissimulava",
                    "egli dissimulava"
                ]
            },
            {
                "persona": "I plur.",
                "verbo": "obtĕgebāmus",
                "traduzioni": [
                    "noi nascondevamo",
                    "noi celavamo",
                    "noi coprivamo",
                    "noi coprivamo",
                    "noi proteggevamo",
                    "noi riparavamo",
                    "noi nascondevamo",
                    "noi dissimulavamo"
                ]
            },
            {
                "persona": "II plur.",
                "verbo": "obtĕgebātis",
                "traduzioni": [
                    "voi nascondevate",
                    "voi celavate",
                    "voi coprivate",
                    "voi coprivate",
                    "voi proteggevate",
                    "voi riparavate",
                    "voi nascondevate",
                    "voi dissimulavate"
                ]
            },
            {
                "persona": "III plur.",
                "verbo": "obtĕgēbant",
                "traduzioni": [
                    "loro nascondevano",
                    "essi nascondevano",
                    "loro celavano",
                    "essi celavano",
                    "loro coprivano",
                    "essi coprivano",
                    "loro coprivano",
                    "essi coprivano",
                    "loro proteggevano",
                    "essi proteggevano",
                    "loro riparavano",
                    "essi riparavano",
                    "loro nascondevano",
                    "essi nascondevano",
                    "loro dissimulavano",
                    "essi dissimulavano"
                ]
            }
        ],
        "FUTURO SEMPLICE": [
            {
                "persona": "I sing.",
                "verbo": "obtĕgam",
                "traduzioni": [
                    "io nasconderò",
                    "io celerò",
                    "io coprirò",
                    "io coprirò",
                    "io proteggerò",
                    "io riparerò",
                    "io nasconderò",
                    "io dissimulerò"
                ]
            },
            {
                "persona": "II sing.",
                "verbo": "obtĕges",
                "traduzioni": [
                    "tu nasconderai",
                    "tu celerai",
                    "tu coprirai",
                    "tu coprirai",
                    "tu proteggerai",
                    "tu riparerai",
                    "tu nasconderai",
                    "tu dissimulerai"
                ]
            },
            {
                "persona": "III sing.",
                "verbo": "obtĕget",
                "traduzioni": [
                    "lui nasconderà",
                    "lei nasconderà",
                    "egli nasconderà",
                    "lui celerà",
                    "lei celerà",
                    "egli celerà",
                    "lui coprirà",
                    "lei coprirà",
                    "egli coprirà",
                    "lui coprirà",
                    "lei coprirà",
                    "egli coprirà",
                    "lui proteggerà",
                    "lei proteggerà",
                    "egli proteggerà",
                    "lui riparerà",
                    "lei riparerà",
                    "egli riparerà",
                    "lui nasconderà",
                    "lei nasconderà",
                    "egli nasconderà",
                    "lui dissimulerà",
                    "lei dissimulerà",
                    "egli dissimulerà"
                ]
            },
            {
                "persona": "I plur.",
                "verbo": "obtĕgēmus",
                "traduzioni": [
                    "noi nasconderemo",
                    "noi celeremo",
                    "noi copriremo",
                    "noi copriremo",
                    "noi proteggeremo",
                    "noi ripareremo",
                    "noi nasconderemo",
                    "noi dissimuleremo"
                ]
            },
            {
                "persona": "II plur.",
                "verbo": "obtĕgētis",
                "traduzioni": [
                    "voi nasconderete",
                    "voi celerete",
                    "voi coprirete",
                    "voi coprirete",
                    "voi proteggerete",
                    "voi riparerete",
                    "voi nasconderete",
                    "voi dissimulerete"
                ]
            },
            {
                "persona": "III plur.",
                "verbo": "obtĕgent",
                "traduzioni": [
                    "loro nasconderanno",
                    "essi nasconderanno",
                    "loro celeranno",
                    "essi celeranno",
                    "loro copriranno",
                    "essi copriranno",
                    "loro copriranno",
                    "essi copriranno",
                    "loro proteggeranno",
                    "essi proteggeranno",
                    "loro ripareranno",
                    "essi ripareranno",
                    "loro nasconderanno",
                    "essi nasconderanno",
                    "loro dissimuleranno",
                    "essi dissimuleranno"
                ]
            }
        ],
        "PERFETTO": [
            {
                "persona": "I sing.",
                "verbo": "obtexi",
                "traduzioni": [
                    "io nascosi",
                    "io ho nascosto",
                    "io ebbi nascosto",
                    "io celai",
                    "io ho celato",
                    "io ebbi celato",
                    "io coprii",
                    "io copersi",
                    "io ho coperto",
                    "io ebbi coperto",
                    "io coprii",
                    "io copersi",
                    "io ho coperto",
                    "io ebbi coperto",
                    "io protessi",
                    "io ho protetto",
                    "io ebbi protetto",
                    "io riparai",
                    "io sono riparato",
                    "io sono riparata",
                    "io fui riparato",
                    "io fui riparata",
                    "io nascosi",
                    "io ho nascosto",
                    "io ebbi nascosto",
                    "io dissimulai",
                    "io ho dissimulato",
                    "io ebbi dissimulato"
                ]
            },
            {
                "persona": "II sing.",
                "verbo": "obtexisti",
                "traduzioni": [
                    "tu nascondesti",
                    "tu hai nascosto",
                    "tu avesti nascosto",
                    "tu celasti",
                    "tu hai celato",
                    "tu avesti celato",
                    "tu copristi",
                    "tu hai coperto",
                    "tu avesti coperto",
                    "tu copristi",
                    "tu hai coperto",
                    "tu avesti coperto",
                    "tu proteggesti",
                    "tu hai protetto",
                    "tu avesti protetto",
                    "tu riparasti",
                    "tu sei riparato",
                    "tu sei riparata",
                    "tu fosti riparato",
                    "tu fosti riparata",
                    "tu nascondesti",
                    "tu hai nascosto",
                    "tu avesti nascosto",
                    "tu dissimulasti",
                    "tu hai dissimulato",
                    "tu avesti dissimulato"
                ]
            },
            {
                "persona": "III sing.",
                "verbo": "obtexit",
                "traduzioni": [
                    "lui nascose",
                    "lei nascose",
                    "egli nascose",
                    "lui ha nascosto",
                    "lei ha nascosto",
                    "egli ha nascosto",
                    "lui ebbe nascosto",
                    "lei ebbe nascosto",
                    "egli ebbe nascosto",
                    "lui celò",
                    "lei celò",
                    "egli celò",
                    "lui ha celato",
                    "lei ha celato",
                    "egli ha celato",
                    "lui ebbe celato",
                    "lei ebbe celato",
                    "egli ebbe celato",
                    "lui coprì",
                    "lei coprì",
                    "egli coprì",
                    "lui coperse",
                    "lei coperse",
                    "egli coperse",
                    "lui ha coperto",
                    "lei ha coperto",
                    "egli ha coperto",
                    "lui ebbe coperto",
                    "lei ebbe coperto",
                    "egli ebbe coperto",
                    "lui coprì",
                    "lei coprì",
                    "egli coprì",
                    "lui coperse",
                    "lei coperse",
                    "egli coperse",
                    "lui ha coperto",
                    "lei ha coperto",
                    "egli ha coperto",
                    "lui ebbe coperto",
                    "lei ebbe coperto",
                    "egli ebbe coperto",
                    "lui protesse",
                    "lei protesse",
                    "egli protesse",
                    "lui ha protetto",
                    "lei ha protetto",
                    "egli ha protetto",
                    "lui ebbe protetto",
                    "lei ebbe protetto",
                    "egli ebbe protetto",
                    "lui riparò",
                    "lei riparò",
                    "egli riparò",
                    "lui è riparato",
                    "lei è riparata",
                    "egli è riparato",
                    "lui fu riparato",
                    "lei fu riparata",
                    "egli fu riparato",
                    "lui nascose",
                    "lei nascose",
                    "egli nascose",
                    "lui ha nascosto",
                    "lei ha nascosto",
                    "egli ha nascosto",
                    "lui ebbe nascosto",
                    "lei ebbe nascosto",
                    "egli ebbe nascosto",
                    "lui dissimulò",
                    "lei dissimulò",
                    "egli dissimulò",
                    "lui ha dissimulato",
                    "lei ha dissimulato",
                    "egli ha dissimulato",
                    "lui ebbe dissimulato",
                    "lei ebbe dissimulato",
                    "egli ebbe dissimulato"
                ]
            },
            {
                "persona": "I plur.",
                "verbo": "obtexĭmus",
                "traduzioni": [
                    "noi nascondemmo",
                    "noi abbiamo nascosto",
                    "noi avemmo nascosto",
                    "noi celammo",
                    "noi abbiamo celato",
                    "noi avemmo celato",
                    "noi coprimmo",
                    "noi abbiamo coperto",
                    "noi avemmo coperto",
                    "noi coprimmo",
                    "noi abbiamo coperto",
                    "noi avemmo coperto",
                    "noi proteggemmo",
                    "noi abbiamo protetto",
                    "noi avemmo protetto",
                    "noi riparammo",
                    "noi siamo riparati",
                    "noi siamo riparate",
                    "noi fummo riparati",
                    "noi fummo riparate",
                    "noi nascondemmo",
                    "noi abbiamo nascosto",
                    "noi avemmo nascosto",
                    "noi dissimulammo",
                    "noi abbiamo dissimulato",
                    "noi avemmo dissimulato"
                ]
            },
            {
                "persona": "II plur.",
                "verbo": "obtexistis",
                "traduzioni": [
                    "voi nascondeste",
                    "voi avete nascosto",
                    "voi aveste nascosto",
                    "voi celaste",
                    "voi avete celato",
                    "voi aveste celato",
                    "voi copriste",
                    "voi avete coperto",
                    "voi aveste coperto",
                    "voi copriste",
                    "voi avete coperto",
                    "voi aveste coperto",
                    "voi proteggeste",
                    "voi avete protetto",
                    "voi aveste protetto",
                    "voi riparaste",
                    "voi siete riparati",
                    "voi siete riparate",
                    "voi foste riparati",
                    "voi foste riparate",
                    "voi nascondeste",
                    "voi avete nascosto",
                    "voi aveste nascosto",
                    "voi dissimulaste",
                    "voi avete dissimulato",
                    "voi aveste dissimulato"
                ]
            },
            {
                "persona": "III plur.",
                "verbo": "obtexērunt, obtexēre",
                "traduzioni": [
                    "loro nascosero",
                    "essi nascosero",
                    "loro hanno nascosto",
                    "essi hanno nascosto",
                    "loro ebbero nascosto",
                    "essi ebbero nascosto",
                    "loro celarono",
                    "essi celarono",
                    "loro hanno celato",
                    "essi hanno celato",
                    "loro ebbero celato",
                    "essi ebbero celato",
                    "loro coprirono",
                    "essi coprirono",
                    "loro copersero",
                    "essi copersero",
                    "loro hanno coperto",
                    "essi hanno coperto",
                    "loro ebbero coperto",
                    "essi ebbero coperto",
                    "loro coprirono",
                    "essi coprirono",
                    "loro copersero",
                    "essi copersero",
                    "loro hanno coperto",
                    "essi hanno coperto",
                    "loro ebbero coperto",
                    "essi ebbero coperto",
                    "loro protessero",
                    "essi protessero",
                    "loro hanno protetto",
                    "essi hanno protetto",
                    "loro ebbero protetto",
                    "essi ebbero protetto",
                    "loro ripararono",
                    "essi ripararono",
                    "loro sono riparati",
                    "loro sono riparate",
                    "essi sono riparati",
                    "loro furono riparati",
                    "loro furono riparate",
                    "essi furono riparati",
                    "loro nascosero",
                    "essi nascosero",
                    "loro hanno nascosto",
                    "essi hanno nascosto",
                    "loro ebbero nascosto",
                    "essi ebbero nascosto",
                    "loro dissimularono",
                    "essi dissimularono",
                    "loro hanno dissimulato",
                    "essi hanno dissimulato",
                    "loro ebbero dissimulato",
                    "essi ebbero dissimulato"
                ]
            }
        ],
        "PIUCHEPERFETTO": [
            {
                "persona": "I sing.",
                "verbo": "obtexĕram",
                "traduzioni": [
                    "io avevo nascosto",
                    "io avevo celato",
                    "io avevo coperto",
                    "io avevo coperto",
                    "io avevo protetto",
                    "io ero riparato",
                    "io ero riparata",
                    "io avevo nascosto",
                    "io avevo dissimulato"
                ]
            },
            {
                "persona": "II sing.",
                "verbo": "obtexĕras",
                "traduzioni": [
                    "tu avevi nascosto",
                    "tu avevi celato",
                    "tu avevi coperto",
                    "tu avevi coperto",
                    "tu avevi protetto",
                    "tu eri riparato",
                    "tu eri riparata",
                    "tu avevi nascosto",
                    "tu avevi dissimulato"
                ]
            },
            {
                "persona": "III sing.",
                "verbo": "obtexĕrat",
                "traduzioni": [
                    "lui aveva nascosto",
                    "lei aveva nascosto",
                    "egli aveva nascosto",
                    "lui aveva celato",
                    "lei aveva celato",
                    "egli aveva celato",
                    "lui aveva coperto",
                    "lei aveva coperto",
                    "egli aveva coperto",
                    "lui aveva coperto",
                    "lei aveva coperto",
                    "egli aveva coperto",
                    "lui aveva protetto",
                    "lei aveva protetto",
                    "egli aveva protetto",
                    "lui era riparato",
                    "lei era riparata",
                    "egli era riparato",
                    "lui aveva nascosto",
                    "lei aveva nascosto",
                    "egli aveva nascosto",
                    "lui aveva dissimulato",
                    "lei aveva dissimulato",
                    "egli aveva dissimulato"
                ]
            },
            {
                "persona": "I plur.",
                "verbo": "obtexerāmus",
                "traduzioni": [
                    "noi avevamo nascosto",
                    "noi avevamo celato",
                    "noi avevamo coperto",
                    "noi avevamo coperto",
                    "noi avevamo protetto",
                    "noi eravamo riparati",
                    "noi eravamo riparate",
                    "noi avevamo nascosto",
                    "noi avevamo dissimulato"
                ]
            },
            {
                "persona": "II plur.",
                "verbo": "obtexerātis",
                "traduzioni": [
                    "voi avevate nascosto",
                    "voi avevate celato",
                    "voi avevate coperto",
                    "voi avevate coperto",
                    "voi avevate protetto",
                    "voi eravate riparati",
                    "voi eravate riparate",
                    "voi avevate nascosto",
                    "voi avevate dissimulato"
                ]
            },
            {
                "persona": "III plur.",
                "verbo": "obtexĕrant",
                "traduzioni": [
                    "loro avevano nascosto",
                    "essi avevano nascosto",
                    "loro avevano celato",
                    "essi avevano celato",
                    "loro avevano coperto",
                    "essi avevano coperto",
                    "loro avevano coperto",
                    "essi avevano coperto",
                    "loro avevano protetto",
                    "essi avevano protetto",
                    "loro erano riparati",
                    "loro erano riparate",
                    "essi erano riparati",
                    "loro avevano nascosto",
                    "essi avevano nascosto",
                    "loro avevano dissimulato",
                    "essi avevano dissimulato"
                ]
            }
        ],
        "FUTURO ANTERIORE": [
            {
                "persona": "I sing.",
                "verbo": "obtexĕro",
                "traduzioni": [
                    "io avrò nascosto",
                    "io avrò celato",
                    "io avrò coperto",
                    "io avrò coperto",
                    "io avrò protetto",
                    "io sarò riparato",
                    "io sarò riparata",
                    "io avrò nascosto",
                    "io avrò dissimulato"
                ]
            },
            {
                "persona": "II sing.",
                "verbo": "obtexĕris",
                "traduzioni": [
                    "tu avrai nascosto",
                    "tu avrai celato",
                    "tu avrai coperto",
                    "tu avrai coperto",
                    "tu avrai protetto",
                    "tu sarai riparato",
                    "tu sarai riparata",
                    "tu avrai nascosto",
                    "tu avrai dissimulato"
                ]
            },
            {
                "persona": "III sing.",
                "verbo": "obtexĕrit",
                "traduzioni": [
                    "lui avrà nascosto",
                    "lei avrà nascosto",
                    "egli avrà nascosto",
                    "lui avrà celato",
                    "lei avrà celato",
                    "egli avrà celato",
                    "lui avrà coperto",
                    "lei avrà coperto",
                    "egli avrà coperto",
                    "lui avrà coperto",
                    "lei avrà coperto",
                    "egli avrà coperto",
                    "lui avrà protetto",
                    "lei avrà protetto",
                    "egli avrà protetto",
                    "lui sarà riparato",
                    "lei sarà riparata",
                    "egli sarà riparato",
                    "lui avrà nascosto",
                    "lei avrà nascosto",
                    "egli avrà nascosto",
                    "lui avrà dissimulato",
                    "lei avrà dissimulato",
                    "egli avrà dissimulato"
                ]
            },
            {
                "persona": "I plur.",
                "verbo": "obtexerĭmus",
                "traduzioni": [
                    "noi avremo nascosto",
                    "noi avremo celato",
                    "noi avremo coperto",
                    "noi avremo coperto",
                    "noi avremo protetto",
                    "noi saremo riparati",
                    "noi saremo riparate",
                    "noi avremo nascosto",
                    "noi avremo dissimulato"
                ]
            },
            {
                "persona": "II plur.",
                "verbo": "obtexerĭtis",
                "traduzioni": [
                    "voi avrete nascosto",
                    "voi avrete celato",
                    "voi avrete coperto",
                    "voi avrete coperto",
                    "voi avrete protetto",
                    "voi sarete riparati",
                    "voi sarete riparate",
                    "voi avrete nascosto",
                    "voi avrete dissimulato"
                ]
            },
            {
                "persona": "III plur.",
                "verbo": "obtexĕrint",
                "traduzioni": [
                    "loro avranno nascosto",
                    "essi avranno nascosto",
                    "loro avranno celato",
                    "essi avranno celato",
                    "loro avranno coperto",
                    "essi avranno coperto",
                    "loro avranno coperto",
                    "essi avranno coperto",
                    "loro avranno protetto",
                    "essi avranno protetto",
                    "loro saranno riparati",
                    "loro saranno riparate",
                    "essi saranno riparati",
                    "loro avranno nascosto",
                    "essi avranno nascosto",
                    "loro avranno dissimulato",
                    "essi avranno dissimulato"
                ]
            }
        ]
    },
    "CONGIUNTIVO": {
        "PRESENTE": [
            {
                "persona": "I sing.",
                "verbo": "obtĕgam",
                "traduzioni": [
                    "che io nasconda",
                    "che io celi",
                    "che io copra",
                    "che io copra",
                    "che io protegga",
                    "che io ripari",
                    "che io nasconda",
                    "che io dissimuli"
                ]
            },
            {
                "persona": "II sing.",
                "verbo": "obtĕgas",
                "traduzioni": [
                    "che tu nasconda",
                    "che tu celi",
                    "che tu copra",
                    "che tu copra",
                    "che tu protegga",
                    "che tu ripari",
                    "che tu nasconda",
                    "che tu dissimuli"
                ]
            },
            {
                "persona": "III sing.",
                "verbo": "obtĕgat",
                "traduzioni": [
                    "che lui nasconda",
                    "che lei nasconda",
                    "che egli nasconda",
                    "che lui celi",
                    "che lei celi",
                    "che egli celi",
                    "che lui copra",
                    "che lei copra",
                    "che egli copra",
                    "che lui copra",
                    "che lei copra",
                    "che egli copra",
                    "che lui protegga",
                    "che lei protegga",
                    "che egli protegga",
                    "che lui ripari",
                    "che lei ripari",
                    "che egli ripari",
                    "che lui nasconda",
                    "che lei nasconda",
                    "che egli nasconda",
                    "che lui dissimuli",
                    "che lei dissimuli",
                    "che egli dissimuli"
                ]
            },
            {
                "persona": "I plur.",
                "verbo": "obtĕgāmus",
                "traduzioni": [
                    "che noi nascondiamo",
                    "che noi celiamo",
                    "che noi copriamo",
                    "che noi copriamo",
                    "che noi proteggiamo",
                    "che noi ripariamo",
                    "che noi nascondiamo",
                    "che noi dissimuliamo"
                ]
            },
            {
                "persona": "II plur.",
                "verbo": "obtĕgātis",
                "traduzioni": [
                    "che voi nascondiate",
                    "che voi celiate",
                    "che voi copriate",
                    "che voi copriate",
                    "che voi proteggiate",
                    "che voi ripariate",
                    "che voi nascondiate",
                    "che voi dissimuliate"
                ]
            },
            {
                "persona": "III plur.",
                "verbo": "obtĕgant",
                "traduzioni": [
                    "che loro nascondano",
                    "che essi nascondano",
                    "che loro celino",
                    "che essi celino",
                    "che loro coprano",
                    "che essi coprano",
                    "che loro coprano",
                    "che essi coprano",
                    "che loro proteggano",
                    "che essi proteggano",
                    "che loro riparino",
                    "che essi riparino",
                    "che loro nascondano",
                    "che essi nascondano",
                    "che loro dissimulino",
                    "che essi dissimulino"
                ]
            }
        ],
        "IMPERFETTO": [
            {
                "persona": "I sing.",
                "verbo": "obtĕgĕrem",
                "traduzioni": [
                    "che io nascondessi",
                    "che io celassi",
                    "che io coprissi",
                    "che io coprissi",
                    "che io proteggessi",
                    "che io riparassi",
                    "che io nascondessi",
                    "che io dissimulassi"
                ]
            },
            {
                "persona": "II sing.",
                "verbo": "obtĕgĕres",
                "traduzioni": [
                    "che tu nascondessi",
                    "che tu celassi",
                    "che tu coprissi",
                    "che tu coprissi",
                    "che tu proteggessi",
                    "che tu riparassi",
                    "che tu nascondessi",
                    "che tu dissimulassi"
                ]
            },
            {
                "persona": "III sing.",
                "verbo": "obtĕgĕret",
                "traduzioni": [
                    "che lui nascondesse",
                    "che lei nascondesse",
                    "che egli nascondesse",
                    "che lui celasse",
                    "che lei celasse",
                    "che egli celasse",
                    "che lui coprisse",
                    "che lei coprisse",
                    "che egli coprisse",
                    "che lui coprisse",
                    "che lei coprisse",
                    "che egli coprisse",
                    "che lui proteggesse",
                    "che lei proteggesse",
                    "che egli proteggesse",
                    "che lui riparasse",
                    "che lei riparasse",
                    "che egli riparasse",
                    "che lui nascondesse",
                    "che lei nascondesse",
                    "che egli nascondesse",
                    "che lui dissimulasse",
                    "che lei dissimulasse",
                    "che egli dissimulasse"
                ]
            },
            {
                "persona": "I plur.",
                "verbo": "obtĕgerēmus",
                "traduzioni": [
                    "che noi nascondessimo",
                    "che noi celassimo",
                    "che noi coprissimo",
                    "che noi coprissimo",
                    "che noi proteggessimo",
                    "che noi riparassimo",
                    "che noi nascondessimo",
                    "che noi dissimulassimo"
                ]
            },
            {
                "persona": "II plur.",
                "verbo": "obtĕgerētis",
                "traduzioni": [
                    "che voi nascondeste",
                    "che voi celaste",
                    "che voi copriste",
                    "che voi copriste",
                    "che voi proteggeste",
                    "che voi riparaste",
                    "che voi nascondeste",
                    "che voi dissimulaste"
                ]
            },
            {
                "persona": "III plur.",
                "verbo": "obtĕgĕrent",
                "traduzioni": [
                    "che loro nascondessero",
                    "che essi nascondessero",
                    "che loro celassero",
                    "che essi celassero",
                    "che loro coprissero",
                    "che essi coprissero",
                    "che loro coprissero",
                    "che essi coprissero",
                    "che loro proteggessero",
                    "che essi proteggessero",
                    "che loro riparassero",
                    "che essi riparassero",
                    "che loro nascondessero",
                    "che essi nascondessero",
                    "che loro dissimulassero",
                    "che essi dissimulassero"
                ]
            }
        ],
        "PERFETTO": [
            {
                "persona": "I sing.",
                "verbo": "obtexĕrim",
                "traduzioni": [
                    "che io abbia nascosto",
                    "che io abbia celato",
                    "che io abbia coperto",
                    "che io abbia coperto",
                    "che io abbia protetto",
                    "che io sia riparato",
                    "che io sia riparata",
                    "che io abbia nascosto",
                    "che io abbia dissimulato"
                ]
            },
            {
                "persona": "II sing.",
                "verbo": "obtexĕris",
                "traduzioni": [
                    "che tu abbia nascosto",
                    "che tu abbia celato",
                    "che tu abbia coperto",
                    "che tu abbia coperto",
                    "che tu abbia protetto",
                    "che tu sia riparato",
                    "che tu sia riparata",
                    "che tu abbia nascosto",
                    "che tu abbia dissimulato"
                ]
            },
            {
                "persona": "III sing.",
                "verbo": "obtexĕrit",
                "traduzioni": [
                    "che lui abbia nascosto",
                    "che lei abbia nascosto",
                    "che egli abbia nascosto",
                    "che lui abbia celato",
                    "che lei abbia celato",
                    "che egli abbia celato",
                    "che lui abbia coperto",
                    "che lei abbia coperto",
                    "che egli abbia coperto",
                    "che lui abbia coperto",
                    "che lei abbia coperto",
                    "che egli abbia coperto",
                    "che lui abbia protetto",
                    "che lei abbia protetto",
                    "che egli abbia protetto",
                    "che lui sia riparato",
                    "che lei sia riparata",
                    "che egli sia riparato",
                    "che lui abbia nascosto",
                    "che lei abbia nascosto",
                    "che egli abbia nascosto",
                    "che lui abbia dissimulato",
                    "che lei abbia dissimulato",
                    "che egli abbia dissimulato"
                ]
            },
            {
                "persona": "I plur.",
                "verbo": "obtexerĭmus",
                "traduzioni": [
                    "che noi abbiamo nascosto",
                    "che noi abbiamo celato",
                    "che noi abbiamo coperto",
                    "che noi abbiamo coperto",
                    "che noi abbiamo protetto",
                    "che noi siamo riparati",
                    "che noi siamo riparate",
                    "che noi abbiamo nascosto",
                    "che noi abbiamo dissimulato"
                ]
            },
            {
                "persona": "II plur.",
                "verbo": "obtexerĭtis",
                "traduzioni": [
                    "che voi abbiate nascosto",
                    "che voi abbiate celato",
                    "che voi abbiate coperto",
                    "che voi abbiate coperto",
                    "che voi abbiate protetto",
                    "che voi siate riparati",
                    "che voi siate riparate",
                    "che voi abbiate nascosto",
                    "che voi abbiate dissimulato"
                ]
            },
            {
                "persona": "III plur.",
                "verbo": "obtexĕrint",
                "traduzioni": [
                    "che loro abbiano nascosto",
                    "che essi abbiano nascosto",
                    "che loro abbiano celato",
                    "che essi abbiano celato",
                    "che loro abbiano coperto",
                    "che essi abbiano coperto",
                    "che loro abbiano coperto",
                    "che essi abbiano coperto",
                    "che loro abbiano protetto",
                    "che essi abbiano protetto",
                    "che loro siano riparati",
                    "che loro siano riparate",
                    "che essi siano riparati",
                    "che loro abbiano nascosto",
                    "che essi abbiano nascosto",
                    "che loro abbiano dissimulato",
                    "che essi abbiano dissimulato"
                ]
            }
        ],
        "PIUCHEPERFETTO": [
            {
                "persona": "I sing.",
                "verbo": "obtexissem",
                "traduzioni": [
                    "che io avessi nascosto",
                    "che io avessi celato",
                    "che io avessi coperto",
                    "che io avessi coperto",
                    "che io avessi protetto",
                    "che io fossi riparato",
                    "che io fossi riparata",
                    "che io avessi nascosto",
                    "che io avessi dissimulato"
                ]
            },
            {
                "persona": "II sing.",
                "verbo": "obtexisses",
                "traduzioni": [
                    "che tu avessi nascosto",
                    "che tu avessi celato",
                    "che tu avessi coperto",
                    "che tu avessi coperto",
                    "che tu avessi protetto",
                    "che tu fossi riparato",
                    "che tu fossi riparata",
                    "che tu avessi nascosto",
                    "che tu avessi dissimulato"
                ]
            },
            {
                "persona": "III sing.",
                "verbo": "obtexisset",
                "traduzioni": [
                    "che lui avesse nascosto",
                    "che lei avesse nascosto",
                    "che egli avesse nascosto",
                    "che lui avesse celato",
                    "che lei avesse celato",
                    "che egli avesse celato",
                    "che lui avesse coperto",
                    "che lei avesse coperto",
                    "che egli avesse coperto",
                    "che lui avesse coperto",
                    "che lei avesse coperto",
                    "che egli avesse coperto",
                    "che lui avesse protetto",
                    "che lei avesse protetto",
                    "che egli avesse protetto",
                    "che lui fosse riparato",
                    "che lei fosse riparata",
                    "che egli fosse riparato",
                    "che lui avesse nascosto",
                    "che lei avesse nascosto",
                    "che egli avesse nascosto",
                    "che lui avesse dissimulato",
                    "che lei avesse dissimulato",
                    "che egli avesse dissimulato"
                ]
            },
            {
                "persona": "I plur.",
                "verbo": "obtexissēmus",
                "traduzioni": [
                    "che noi avessimo nascosto",
                    "che noi avessimo celato",
                    "che noi avessimo coperto",
                    "che noi avessimo coperto",
                    "che noi avessimo protetto",
                    "che noi fossimo riparati",
                    "che noi fossimo riparate",
                    "che noi avessimo nascosto",
                    "che noi avessimo dissimulato"
                ]
            },
            {
                "persona": "II plur.",
                "verbo": "obtexissētis",
                "traduzioni": [
                    "che voi aveste nascosto",
                    "che voi aveste celato",
                    "che voi aveste coperto",
                    "che voi aveste coperto",
                    "che voi aveste protetto",
                    "che voi foste riparati",
                    "che voi foste riparate",
                    "che voi aveste nascosto",
                    "che voi aveste dissimulato"
                ]
            },
            {
                "persona": "III plur.",
                "verbo": "obtexissent",
                "traduzioni": [
                    "che loro avessero nascosto",
                    "che essi avessero nascosto",
                    "che loro avessero celato",
                    "che essi avessero celato",
                    "che loro avessero coperto",
                    "che essi avessero coperto",
                    "che loro avessero coperto",
                    "che essi avessero coperto",
                    "che loro avessero protetto",
                    "che essi avessero protetto",
                    "che loro fossero riparati",
                    "che loro fossero riparate",
                    "che essi fossero riparati",
                    "che loro avessero nascosto",
                    "che essi avessero nascosto",
                    "che loro avessero dissimulato",
                    "che essi avessero dissimulato"
                ]
            }
        ]
    }
}